xgboost_genetic
