Metadata-Version: 2.1
Name: xgboost-genetic
Version: 0.0.2
Summary: Biblioteca para otimização de hiperparâmetros do XGBoost usando algoritmos genéticos.
Home-page: https://github.com/PauloDoMonte/xgboost_genetic
Author: Paulo Do Monte
Author-email: paulo.monte.fis@gmail.com
License: UNKNOWN
Platform: UNKNOWN
Classifier: Programming Language :: Python :: 3
Classifier: License :: OSI Approved :: MIT License
Classifier: Operating System :: OS Independent
Requires-Python: >=3.6
License-File: LICENSE
